src/textual/__init__.py
src/textual/_animator.py
src/textual/_ansi_sequences.py
src/textual/_callback.py
src/textual/_context.py
src/textual/_easing.py
src/textual/_event_broker.py
src/textual/_layout_resolve.py
src/textual/_line_cache.py
src/textual/_lines.py
src/textual/_loop.py
src/textual/_parser.py
src/textual/_profile.py
src/textual/_timer.py
src/textual/_types.py
src/textual/_xterm_parser.py
src/textual/actions.py
src/textual/app.py
src/textual/background.py
src/textual/binding.py
src/textual/case.py
src/textual/driver.py
src/textual/drivers/__init__.py
src/textual/drivers/linux_driver.py
src/textual/drivers/win32.py
src/textual/drivers/windows_driver.py
src/textual/events.py
src/textual/geometry.py
src/textual/keys.py
src/textual/layout.py
src/textual/layout_map.py
src/textual/layouts/__init__.py
src/textual/layouts/dock.py
src/textual/layouts/grid.py
src/textual/layouts/vertical.py
src/textual/message.py
src/textual/message_pump.py
src/textual/messages.py
src/textual/page.py
src/textual/py.typed
src/textual/reactive.py
src/textual/richreadme.md
src/textual/screen_update.py
src/textual/scrollbar.py
src/textual/view.py
src/textual/views/__init__.py
src/textual/views/_dock_view.py
src/textual/views/_document_view.py
src/textual/views/_grid_view.py
src/textual/views/_window_view.py
src/textual/widget.py
src/textual/widgets/__init__.py
src/textual/widgets/_button.py
src/textual/widgets/_directory_tree.py
src/textual/widgets/_footer.py
src/textual/widgets/_header.py
src/textual/widgets/_placeholder.py
src/textual/widgets/_scroll_view.py
src/textual/widgets/_static.py
src/textual/widgets/_tree_control.py
textual_stub-0.1.17.dist-info/LICENSE
textual_stub-0.1.17.dist-info/WHEEL
textual_stub-0.1.17.dist-info/METADATA
textual_stub-0.1.17.dist-info/RECORD
